LICENSE
README.md
setup.py
twprefix/__init__.py
twprefix/__main__.py
twprefix/__version__.py
twprefix/twprefix.py
twprefix.egg-info/PKG-INFO
twprefix.egg-info/SOURCES.txt
twprefix.egg-info/dependency_links.txt
twprefix.egg-info/entry_points.txt
twprefix.egg-info/top_level.txt